flop/__init__.py
flop/hardconcrete.py
flop/linear.py
flop/train.py
flop/utils.py
flop/version.py
flop-1.0.2.dist-info/METADATA
flop-1.0.2.dist-info/WHEEL
flop-1.0.2.dist-info/dependency_links.txt
flop-1.0.2.dist-info/top_level.txt
flop-1.0.2.dist-info/zip-safe
flop-1.0.2.dist-info/RECORD
